{"eid": "2-s2.0-85173562304", "doi": "10.1038/s41524-023-01136-y", "pii": null, "pubmed_id": null, "title": "Accelerating GW calculations through machine-learned dielectric matrices", "subtype": "ar", "subtypeDescription": "Article", "creator": "Zauchner M.G.", "afid": null, "affilname": "Imperial College London", "affiliation_city": "London", "affiliation_country": "United Kingdom", "author_count": null, "author_names": null, "author_ids": null, "author_afids": null, "coverDate": "2023-12-01", "coverDisplayDate": "December 2023", "publicationName": "npj Computational Materials", "issn": null, "source_id": "21100850798", "eIssn": "20573960", "aggregationType": "Journal", "volume": "9", "issueIdentifier": "1", "article_number": "184", "pageRange": null, "description": null, "authkeywords": null, "citedby_count": 1, "openaccess": 1, "freetoread": "repositoryam", "freetoreadLabel": "Green", "fund_acr": null, "fund_no": null, "fund_sponsor": null, "ref_docs": [{"doi": "10.1103/PhysRev.136.B864", "title": "Inhomogeneous electron gas", "id": "10644250257", "sourcetitle": "Physical Review"}, {"doi": "10.1103/PhysRev.140.A1133", "title": "Self-consistent equations including exchange and correlation effects", "id": "0042113153", "sourcetitle": "Physical Review"}, {"doi": "10.1103/PhysRevLett.51.1888", "title": "Density-functional theory of the energy gap", "id": "4243209020", "sourcetitle": "Physical Review Letters"}, {"doi": "10.1103/PhysRevLett.96.246401", "title": "Theory of defect levels and the \"band gap problem\" in silicon", "id": "33745257027", "sourcetitle": "Physical Review Letters"}, {"doi": "10.1103/PhysRev.139.A796", "title": "New method for calculating the one-particle Green's function with application to the electron-gas problem", "id": "36149016819", "sourcetitle": "Physical Review"}, {"doi": "10.1103/PhysRevB.25.2867", "title": "Dynamical aspects of correlation corrections in a covalent crystal", "id": "0001634713", "sourcetitle": "Physical Review B"}, {"doi": "10.1103/PhysRevB.34.5390", "title": "Electron correlation in semiconductors and insulators: Band gaps and quasiparticle energies", "id": "25544479230", "sourcetitle": "Physical Review B"}, {"doi": "10.1103/RevModPhys.74.601", "title": "Electronic excitations: Density-functional versus many-body Green's-function approaches", "id": "0036057017", "sourcetitle": "Reviews of Modern Physics"}, {"doi": "10.1103/PhysRevB.82.205127", "title": "Electronic excitations from a perturbative LDA+GdW approach", "id": "78649756477", "sourcetitle": "Physical Review B - Condensed Matter and Materials Physics"}, {"doi": "10.1103/PhysRev.126.413", "title": "Quantum theory of the dielectric constant in real solids", "id": "36149012924", "sourcetitle": "Physical Review"}, {"doi": "10.1103/PhysRev.129.62", "title": "Dielectric constant with local field effects included", "id": "0002237407", "sourcetitle": "Physical Review"}, {"doi": "10.1016/j.cpc.2018.09.003", "title": "Large-scale GW calculations on pre-exascale HPC systems", "id": "85053914911", "sourcetitle": "Computer Physics Communications"}, {"doi": "10.1021/ct500958p", "title": "Large Scale GW Calculations", "id": "84931287893", "sourcetitle": "Journal of Chemical Theory and Computation"}, {"doi": "10.1021/acs.jpclett.7b02740", "title": "Toward GW Calculations on Thousands of Atoms", "id": "85040718591", "sourcetitle": "Journal of Physical Chemistry Letters"}, {"doi": "10.1021/acs.jctc.0c00693", "title": "Low-Order Scaling G0W0by Pair Atomic Density Fitting", "id": "85096553401", "sourcetitle": "Journal of Chemical Theory and Computation"}, {"doi": "10.1021/acs.jctc.1c00101", "title": "Cubic-Scaling All-Electron GW Calculations with a Separable Density-Fitting Space-Time Approach", "id": "85104276420", "sourcetitle": "Journal of Chemical Theory and Computation"}, {"doi": "10.1103/PhysRevB.37.2733", "title": "Model dielectric matrices for quasiparticle self-energy calculations", "id": "33744613686", "sourcetitle": "Physical Review B"}, {"doi": "10.1103/PhysRevB.47.9892", "title": "Model dielectric function for semiconductors", "id": "0001271179", "sourcetitle": "Physical Review B"}, {"doi": "10.1016/0038-1098(92)90476-P", "title": "An efficient method for calculating quasiparticle energies in semiconductors", "id": "0026945539", "sourcetitle": "Solid State Communications"}, {"doi": "10.1103/PhysRevB.99.014104", "title": "Atomic cluster expansion for accurate and transferable interatomic potentials", "id": "85059877830", "sourcetitle": "Physical Review B"}, {"doi": "10.1103/PhysRevLett.104.136403", "title": "Gaussian approximation potentials: The accuracy of quantum mechanics, without the electrons", "id": "77950441864", "sourcetitle": "Physical Review Letters"}, {"doi": "10.1021/ct400195d", "title": "Assessment and validation of machine learning methods for predicting molecular atomization energies", "id": "84882415695", "sourcetitle": "Journal of Chemical Theory and Computation"}, {"doi": "10.1103/PhysRevLett.108.058301", "title": "Fast and accurate modeling of molecular atomization energies with machine learning", "id": "84856512353", "sourcetitle": "Physical Review Letters"}, {"doi": "10.1021/acs.jpclett.5b00831", "title": "Machine learning predictions of molecular properties: Accurate many-body potentials and nonlocality in chemical space", "id": "84935014439", "sourcetitle": "Journal of Physical Chemistry Letters"}, {"doi": "10.1103/PhysRevLett.120.036002", "title": "Symmetry-Adapted Machine Learning for Tensorial Properties of Atomistic Systems", "id": "85040714073", "sourcetitle": "Physical Review Letters"}, {"doi": "10.1073/pnas.1816132116", "title": "Accurate molecular polarizabilities with coupled cluster theory and machine learning", "id": "85062028573", "sourcetitle": "Proceedings of the National Academy of Sciences of the United States of America"}, {"doi": "10.1063/5.0009106", "title": "Predicting molecular dipole moments by combining atomic partial charges and atomic dipoles", "id": "85088157828", "sourcetitle": "Journal of Chemical Physics"}, {"doi": "10.1021/acscentsci.8b00551", "title": "Transferable Machine-Learning Model of the Electron Density", "id": "85059632804", "sourcetitle": "ACS Central Science"}, {"doi": "10.1038/s41467-017-00839-3", "title": "Bypassing the Kohn-Sham equations with machine learning", "id": "85031128428", "sourcetitle": "Nature Communications"}, {"doi": "10.1016/j.compscitech.2018.03.035", "title": "Machine learning electron density in sulfur crosslinked carbon nanotubes", "id": "85045113268", "sourcetitle": "Composites Science and Technology"}, {"doi": "10.1038/s41524-019-0162-7", "title": "Solving the electronic structure problem with machine learning", "id": "85061740850", "sourcetitle": "npj Computational Materials"}, {"doi": null, "title": "Clebsch-Gordan nets: A fully fourier space spherical convolutional neural network", "id": "85064831359", "sourcetitle": "Advances in Neural Information Processing Systems"}, {"doi": null, "title": "On the generalization of equivariance and convolution in neural networks to the action of compact groups", "id": "85055132564", "sourcetitle": "In Proceedings of the 35Th International Conference on Machine Learning"}, {"doi": null, "title": "Cormorant: Covariant molecular neural networks", "id": "85089490731", "sourcetitle": "Advances in Neural Information Processing Systems"}, {"doi": null, "title": null, "id": "85055119773", "sourcetitle": "Tensor field networks: Rotation- and translation-equivariant neural networks for 3D point clouds."}, {"doi": null, "title": null, "id": "85173560659", "sourcetitle": null}, {"doi": null, "title": "Group equivariant convolutional networks", "id": "84998538835", "sourcetitle": "Proceedings of the 33Rd International Conference on Machine Learning"}, {"doi": null, "title": null, "id": "85162187757", "sourcetitle": "Euclidean neural networks (E3nn) v1.0"}, {"doi": null, "title": null, "id": "85173563559", "sourcetitle": null}, {"doi": "10.1039/d1sc01542g", "title": "Physically inspired deep learning of molecular excitations and photoemission spectra", "id": "85112534825", "sourcetitle": "Chemical Science"}, {"doi": "10.1038/s41467-022-28122-0", "title": "Representing individual electronic states for machine learning GW band structures of 2D materials", "id": "85124061855", "sourcetitle": "Nature Communications"}, {"doi": "10.1021/acs.chemmater.1c04279", "title": "Accurate Computational Prediction of Core-Electron Binding Energies in Carbon-Based Materials: A Machine-Learning Model Combining Density-Functional Theory and GW", "id": "85135248837", "sourcetitle": "Chemistry of Materials"}, {"doi": "10.1103/PhysRevLett.55.1418", "title": "First-principles theory of quasiparticles: Calculation of band gaps in semiconductors and insulators", "id": "0001110771", "sourcetitle": "Physical Review Letters"}, {"doi": "10.1103/PhysRevB.90.115130", "title": "Effects of self-consistency and plasmon-pole models on GW calculations for closed-shell molecules", "id": "84907257159", "sourcetitle": "Physical Review B - Condensed Matter and Materials Physics"}, {"doi": null, "title": "Quantitative molecular orbital energies within a G0W0 approximation", "id": "84870412622", "sourcetitle": "Eur. Phys. J. B"}, {"doi": null, "title": null, "id": "85173570358", "sourcetitle": null}, {"doi": "10.1016/j.comptc.2014.10.039", "title": "Relationships between charge density response functions, exchange holes and localized orbitals", "id": "84920847893", "sourcetitle": "Computational and Theoretical Chemistry"}, {"doi": "10.1103/PhysRevB.87.184115", "title": "On representing chemical environments", "id": "84878571921", "sourcetitle": "Physical Review B - Condensed Matter and Materials Physics"}, {"doi": null, "title": null, "id": "0003645841", "sourcetitle": "Elementary Theory of Angular Momentum 1st edn. Structure of matter series"}, {"doi": "10.1002/qua.25639", "title": "Accelerating Kohn-Sham response theory using density fitting and the auxiliary-density-matrix method", "id": "85046653425", "sourcetitle": "International Journal of Quantum Chemistry"}, {"doi": "10.1103/PhysRevB.73.205334", "title": "Optical excitations in organic molecules, clusters, and defects studied by first-principles Green's function methods", "id": "33646734839", "sourcetitle": "Physical Review B - Condensed Matter and Materials Physics"}, {"doi": "10.1038/s41524-022-00721-x", "title": "Representations of molecules and materials for interpolation of quantum-mechanical simulations via machine learning", "id": "85127323798", "sourcetitle": "npj Computational Materials"}, {"doi": "10.1103/PhysRevLett.114.096405", "title": "Molecular dynamics with on-the-fly machine learning of quantum-mechanical forces", "id": "84924365603", "sourcetitle": "Physical Review Letters"}, {"doi": "10.1088/2632-2153/ac2cfe", "title": "Predicting polarizabilities of silicon clusters using local chemical environments", "id": "85123694263", "sourcetitle": "Machine Learning: Science and Technology"}, {"doi": null, "title": null, "id": "85008964047", "sourcetitle": "Silicon quantum dot data set."}, {"doi": "10.1016/j.cpc.2011.12.006", "title": "BerkeleyGW: A massively parallel computer package for the calculation of the quasiparticle and optical properties of materials and nanostructures", "id": "84857703319", "sourcetitle": "Computer Physics Communications"}, {"doi": "10.1088/1361-648X/aa8f79", "title": "Advanced capabilities for materials modelling with Quantum ESPRESSO", "id": "85036470554", "sourcetitle": "Journal of Physics Condensed Matter"}, {"doi": "10.1088/0953-8984/21/39/395502", "title": "QUANTUM ESPRESSO: A modular and open-source software project for quantum simulations of materials", "id": "70349568754", "sourcetitle": "Journal of Physics Condensed Matter"}, {"doi": "10.1103/PhysRevB.87.165124", "title": "Coulomb-hole summations and energies for GW calculations with limited number of empty orbitals: A modified static remainder approach", "id": "84877056268", "sourcetitle": "Physical Review B - Condensed Matter and Materials Physics"}, {"doi": null, "title": null, "id": "84896547056", "sourcetitle": "Libint: A library for the evaluation of molecular integrals of many-body operators over Gaussian functions"}, {"doi": "10.1002/qua.560540202", "title": "Transformation between Cartesian and pure spherical harmonic Gaussians", "id": "84987108750", "sourcetitle": "International Journal of Quantum Chemistry"}, {"doi": "10.1088/0953-4075/30/11/007", "title": "Molecular integrals over spherical Gaussian-type orbitals: I", "id": "0010324808", "sourcetitle": "Journal of Physics B: Atomic, Molecular and Optical Physics"}, {"doi": "10.1016/j.cpc.2019.106949", "title": "DScribe: Library of descriptors for machine learning in materials science", "id": "85072705473", "sourcetitle": "Computer Physics Communications"}, {"doi": null, "title": null, "id": "85164291259", "sourcetitle": "Accelerating GW calculations through machine learned dielectric matrices"}]}