{"eid": "2-s2.0-84936769407", "doi": "10.1590/S1517-707620150002.0039", "pii": null, "pubmed_id": null, "title": "Classifiers performance evaluation in quantitative metallography", "subtype": "ar", "subtypeDescription": "Article", "creator": "Sarruf B.J.M.", "afid": null, "affilname": "Universidade Federal do Rio de Janeiro", "affiliation_city": "Rio de Janeiro", "affiliation_country": "Brazil", "author_count": null, "author_names": null, "author_ids": null, "author_afids": null, "coverDate": "2015-07-08", "coverDisplayDate": "8 July 2015", "publicationName": "Revista Materia", "issn": "15177076", "source_id": "17700155039", "eIssn": null, "aggregationType": "Journal", "volume": "20", "issueIdentifier": "2", "article_number": null, "pageRange": "384-391", "description": null, "authkeywords": null, "citedby_count": 0, "openaccess": 1, "freetoread": "publisherfullgold", "freetoreadLabel": "Gold", "fund_acr": null, "fund_no": null, "fund_sponsor": null, "ref_docs": [{"doi": "10.1017/S1431927605050415", "title": "Automatic classification of graphite in cast iron", "id": "23844511335", "sourcetitle": "Microscopy and Microanalysis"}, {"doi": "10.1021/ci060149f", "title": "Melting point prediction employing k-nearest neighbor algorithms and genetic parameter optimization", "id": "33845748728", "sourcetitle": "Journal of Chemical Information and Modeling"}, {"doi": "10.1109/72.80230", "title": "Perceptron-Based Learning Algorithms", "id": "0025449027", "sourcetitle": "IEEE Transactions on Neural Networks"}, {"doi": null, "title": null, "id": "0003710380", "sourcetitle": "LIBSVM: A library for support vector machines"}, {"doi": null, "title": null, "id": "84936795165", "sourcetitle": "ACM International Conference Proceeding Series"}, {"doi": "10.1016/j.engappai.2005.12.006", "title": "Support vector machines versus multi-layer perceptrons for efficient off-line signature recognition", "id": "33747881516", "sourcetitle": "Engineering Applications of Artificial Intelligence"}, {"doi": null, "title": "Aplica\u00e7\u00e3o dos \u00cdndices KAPPA & PABAK na valida-\u00e7\u00e3o da classifica\u00e7\u00e3o autom\u00e1tica de imagem de sat\u00e9lite em Feira de Santana-BA", "id": "84936795166", "sourcetitle": "Anais XII Simp\u00f3sio Brasileiro de Sensoriamento Remoto"}]}