{"eid": "2-s2.0-85136329278", "doi": "10.1016/j.commatsci.2022.111710", "pii": "S0927025622004311", "pubmed_id": null, "title": "Data-driven modeling of an elastomer bushing system under various visco-hyperelastic deformations", "subtype": "ar", "subtypeDescription": "Article", "creator": "Daareyni A.", "afid": null, "affilname": "University of Tehran", "affiliation_city": "Tehran", "affiliation_country": "Iran", "author_count": null, "author_names": null, "author_ids": null, "author_afids": null, "coverDate": "2022-11-01", "coverDisplayDate": "November 2022", "publicationName": "Computational Materials Science", "issn": "09270256", "source_id": "20541", "eIssn": null, "aggregationType": "Journal", "volume": "214", "issueIdentifier": null, "article_number": "111710", "pageRange": null, "description": null, "authkeywords": null, "citedby_count": 1, "openaccess": 0, "freetoread": null, "freetoreadLabel": null, "fund_acr": null, "fund_no": null, "fund_sponsor": null, "ref_docs": [{"doi": "10.5254/1.3538491", "title": "Specialty elastomers for automotive applications", "id": "0032108278", "sourcetitle": "Rubber Chemistry and Technology"}, {"doi": "10.1061/(ASCE)0733-9445(1983)109:12(2853)", "title": "Elastomeric bearings: State-of-the-art", "id": "0020952012", "sourcetitle": "Journal of Structural Engineering (United States)"}, {"doi": null, "title": "Performance of elastomers in isolation bearings: a literature review", "id": "0038911766", "sourcetitle": "Earthquake spectra"}, {"doi": "10.1016/S0894-9166(11)60004-9", "title": "Theory of dielectric elastomers", "id": "78650965078", "sourcetitle": "Acta Mechanica Solida Sinica"}, {"doi": "10.1006/jsvi.1998.1883", "title": "On the modelling of non-linear elastomeric vibration isolators", "id": "0032762040", "sourcetitle": "Journal of Sound and Vibration"}, {"doi": "10.1016/j.finel.2017.10.009", "title": "Developing a visco-hyperelastic material model for 3D finite deformation of elastomers", "id": "85033395228", "sourcetitle": "Finite Elements in Analysis and Design"}, {"doi": "10.1007/s11340-016-0236-0", "title": "On the Correlation of FEM and Experiments for Hyperelastic Elastomers", "id": "84992347100", "sourcetitle": "Experimental Mechanics"}, {"doi": "10.5254/1.3547602", "title": "Constitutive models of rubber elasticity: A review", "id": "0034216714", "sourcetitle": "Rubber Chemistry and Technology"}, {"doi": "10.1115/1.4047776", "title": "A Review of Physically Based and Thermodynamically Based Constitutive Models for Soft Materials", "id": "85089601890", "sourcetitle": "Journal of Applied Mechanics, Transactions ASME"}, {"doi": null, "title": "Stress-strain data for vulcanized rubber under various types of deformation", "id": "75349083263", "sourcetitle": "Rubber Chem. Technol."}, {"doi": "10.1016/S0022-5096(97)00075-6", "title": "Constitutive modeling of the large strain time-dependent behavior of elastomers", "id": "0032066417", "sourcetitle": "Journal of the Mechanics and Physics of Solids"}, {"doi": "10.1063/1.1955445", "title": "Constrained Rouse model of rubber viscoelasticity", "id": "23744502959", "sourcetitle": "Journal of Chemical Physics"}, {"doi": "10.1016/0093-6413(85)90075-8", "title": "A model of rubber viscoelasticity", "id": "46549097431", "sourcetitle": "Mechanics Research Communications"}, {"doi": "10.1063/1.1724109", "title": "A New Approach to the Theory of Relaxing Polymeric Media", "id": "84953653031", "sourcetitle": "Journal of Chemical Physics"}, {"doi": "10.1016/j.ijsolstr.2020.10.022", "title": "Effect of viscoelasticity on the nonlinear dynamic behavior of dielectric elastomer minimum energy structures", "id": "85096190655", "sourcetitle": "International Journal of Solids and Structures"}, {"doi": "10.1007/s11071-021-06392-5", "title": "Nonlinear oscillations of electrically driven aniso-visco-hyperelastic dielectric elastomer minimum energy structures", "id": "85104070240", "sourcetitle": "Nonlinear Dynamics"}, {"doi": "10.1016/j.ijengsci.2014.03.001", "title": "A visco-hyperelastic constitutive model for rubber-like materials: A rate-dependent relaxation time scheme", "id": "84898403032", "sourcetitle": "International Journal of Engineering Science"}, {"doi": "10.1016/j.compstruc.2021.106620", "title": "An open-source FEniCS-based framework for hyperelastic parameter estimation from noisy full-field data: Application to heterogeneous soft tissues", "id": "85110293423", "sourcetitle": "Computers and Structures"}, {"doi": "10.1016/j.finel.2012.05.001", "title": "A viscoelastic constitutive model for compressible polymers based on logarithmic strain and its finite element implementation", "id": "84865050326", "sourcetitle": "Finite Elements in Analysis and Design"}, {"doi": null, "title": null, "id": "85136328334", "sourcetitle": null}, {"doi": "10.1111/1467-9868.00294", "title": "Bayesian calibration of computer models", "id": "0035648165", "sourcetitle": "Journal of the Royal Statistical Society. Series B: Statistical Methodology"}, {"doi": "10.1016/j.commatsci.2021.110747", "title": "Optimal experimental design with fast neural network surrogate models", "id": "85112686006", "sourcetitle": "Computational Materials Science"}, {"doi": "10.1016/j.commatsci.2021.110829", "title": "Neural network potential for studying the thermal conductivity of Sn", "id": "85114127016", "sourcetitle": "Computational Materials Science"}, {"doi": "10.1016/j.commatsci.2021.110730", "title": "Prediction of the Curie temperatures of ferroelectric solid solutions using machine learning methods", "id": "85110574403", "sourcetitle": "Computational Materials Science"}, {"doi": null, "title": null, "id": "85136325421", "sourcetitle": null}, {"doi": null, "title": null, "id": "85136331416", "sourcetitle": null}, {"doi": null, "title": null, "id": "85136321578", "sourcetitle": null}, {"doi": null, "title": null, "id": "85136332463", "sourcetitle": null}, {"doi": "10.1016/j.commatsci.2022.111286", "title": "Optimization of the elastic properties of block copolymers using coarse-grained simulation and an artificial neural network", "id": "85125377373", "sourcetitle": "Computational Materials Science"}, {"doi": "10.1016/j.commatsci.2021.111181", "title": "Improving prediction accuracy of high-performance materials via modified machine learning strategy", "id": "85122311377", "sourcetitle": "Computational Materials Science"}, {"doi": "10.1007/s00466-021-02112-3", "title": "A Bayesian multiscale CNN framework to predict local stress fields in structures with microscale features", "id": "85120076406", "sourcetitle": "Computational Mechanics"}, {"doi": "10.1007/s00707-003-1018-1", "title": "Elastomer bushing response: Experiments and finite element modeling", "id": "0042342747", "sourcetitle": "Acta Mechanica"}, {"doi": "10.1088/0508-3443/5/10/305", "title": "Load-deflexion relations of rubber bush mountings", "id": "0002948925", "sourcetitle": "British Journal of Applied Physics"}, {"doi": "10.5254/1.3536198", "title": "APPLICATION OF FINITE-ELEMENT ANALYSIS IN THE DESIGN OF AUTOMOTIVE ELASTOMERIC COMPONENTS.", "id": "0024050713", "sourcetitle": "Rubber Chemistry and Technology"}, {"doi": "10.1016/S0020-7403(98)00023-X", "title": "A nonlinear viscoelastic model for one dimensional response of elastomeric bushings", "id": "0032340620", "sourcetitle": "International Journal of Mechanical Sciences"}, {"doi": null, "title": null, "id": "85136323020", "sourcetitle": null}, {"doi": "10.1007/BF01181853", "title": "A constitutive model for carbon black filled rubber: Experimental investigations and mathematical representation", "id": "0004768924", "sourcetitle": "Continuum Mechanics and Thermodynamics"}, {"doi": "10.1016/j.ijmecsci.2019.06.019", "title": "A new hyper-viscoelastic model for investigating rate dependent mechanical behavior of dual cross link self-healing hydrogel", "id": "85066980569", "sourcetitle": "International Journal of Mechanical Sciences"}, {"doi": "10.1038/s41467-017-00030-8", "title": "Chaos as an intermittently forced linear system", "id": "85019971668", "sourcetitle": "Nature Communications"}, {"doi": "10.1007/s00332-015-9258-5", "title": "A Data\u2013Driven Approximation of the Koopman Operator: Extending Dynamic Mode Decomposition", "id": "84945465279", "sourcetitle": "Journal of Nonlinear Science"}, {"doi": null, "title": null, "id": "85136325070", "sourcetitle": null}, {"doi": null, "title": null, "id": "85136327021", "sourcetitle": null}, {"doi": null, "title": null, "id": "85136328281", "sourcetitle": null}, {"doi": null, "title": "Dynamic mode decomposition of experimental data, in 8th International Symposium on Particle Image Velocimetry (PIV09)", "id": "84861807511", "sourcetitle": null}, {"doi": "10.1016/j.cma.2017.11.013", "title": "Data-based derivation of material response", "id": "85037535548", "sourcetitle": "Computer Methods in Applied Mechanics and Engineering"}, {"doi": "10.1137/15M1013857", "title": "Dynamic mode decomposition with control", "id": "84964068387", "sourcetitle": "SIAM Journal on Applied Dynamical Systems"}, {"doi": "10.1038/s41467-018-07210-0", "title": "Deep learning for universal linear embeddings of nonlinear dynamics", "id": "85057132018", "sourcetitle": "Nature Communications"}, {"doi": null, "title": null, "id": "85136327616", "sourcetitle": null}, {"doi": null, "title": "Backpropagation learning for multilayer feed-forward neural networks using the conjugate gradient method", "id": "0000293377", "sourcetitle": "Int. J. Neural Syst."}, {"doi": null, "title": "Analysis of Levenberg-Marquardt and Scaled Conjugate Gradient Training Algorithms for Artificial Neural Network Based LS and MMSE Estimated Channel Equalizers", "id": "85136319754", "sourcetitle": null}, {"doi": null, "title": null, "id": "85136339190", "sourcetitle": null}, {"doi": "10.1016/j.euromechsol.2012.09.010", "title": "A hyperelastic constitutive model for rubber-like materials", "id": "84870702196", "sourcetitle": "European Journal of Mechanics, A/Solids"}, {"doi": null, "title": null, "id": "85136334421", "sourcetitle": null}, {"doi": "10.1007/s10999-013-9228-8", "title": "Finite strain numerical analysis of elastomeric bushings under multi-axial loadings: A compressible visco-hyperelastic approach", "id": "84889066186", "sourcetitle": "International Journal of Mechanics and Materials in Design"}, {"doi": null, "title": "Large deformation of hyperelastic thick-walled vessels under combined extension-torsion-pressure: analytical solution and FEM", "id": "85114961890", "sourcetitle": "Mechanics Based Design of Structures and Machines"}, {"doi": "10.1016/j.ijmecsci.2019.04.053", "title": "Closed form solutions for large deformation of cylinders under combined extension-torsion", "id": "85064889454", "sourcetitle": "International Journal of Mechanical Sciences"}, {"doi": "10.1007/s11043-013-9208-2", "title": "Non-linear approach in visco-hyperelastic constitutive modelling of polyurethane nanocomposite", "id": "84900646807", "sourcetitle": "Mechanics of Time-Dependent Materials"}, {"doi": "10.1016/j.ijmecsci.2021.106560", "title": "Development of a large strain formulation for multiple shape-memory-effect of polymers under bending", "id": "85109082174", "sourcetitle": "International Journal of Mechanical Sciences"}, {"doi": "10.1016/j.tice.2013.12.004", "title": "A visco-hyperelastic constitutive approach for modeling polyvinyl alcohol sponge", "id": "84895906321", "sourcetitle": "Tissue and Cell"}, {"doi": "10.1007/s00707-009-0239-3", "title": "Hyperelastic materials behavior modeling using consistent strain energy density functions", "id": "84898033715", "sourcetitle": "Acta Mechanica"}, {"doi": "10.1016/j.ijpharm.2021.121184", "title": "Computational analysis of vincristine loaded silk fibroin hydrogel for sustained drug delivery applications: Multiphysics modeling and experiments", "id": "85117146202", "sourcetitle": "International Journal of Pharmaceutics"}, {"doi": "10.1007/s11242-021-01643-w", "title": "An Electrodiffusion Model Coupled with Fluid-Flow Effects for an On-Chip Electromembrane Extraction System", "id": "85109274995", "sourcetitle": "Transport in Porous Media"}]}