{"eid": "2-s2.0-85119440609", "doi": "10.1080/02670836.2021.2001731", "pii": null, "pubmed_id": null, "title": "Assessing the implementation of machine learning models for thermal treatments design", "subtype": "ar", "subtypeDescription": "Article", "creator": "Eres-Castellanos A.", "afid": null, "affilname": "CSIC - Centro Nacional de Investigaciones Metalurgicas (CENIM)", "affiliation_city": "Madrid", "affiliation_country": "Spain", "author_count": null, "author_names": null, "author_ids": null, "author_afids": null, "coverDate": "2021-01-01", "coverDisplayDate": "2021", "publicationName": "Materials Science and Technology (United Kingdom)", "issn": "02670836", "source_id": "17815", "eIssn": "17432847", "aggregationType": "Journal", "volume": "37", "issueIdentifier": "16", "article_number": null, "pageRange": "1302-1310", "description": null, "authkeywords": null, "citedby_count": 2, "openaccess": 1, "freetoread": "repositoryvor", "freetoreadLabel": "Green", "fund_acr": null, "fund_no": null, "fund_sponsor": null, "ref_docs": [{"doi": null, "title": "Empirical formulae for the calculation of some transformation temperatures", "id": "0000838199", "sourcetitle": "J Iron Steel Inst"}, {"doi": null, "title": "Martensite reactions in alloy steels", "id": "0001219652", "sourcetitle": "Trans Am Soc Met"}, {"doi": null, "title": null, "id": "85119422253", "sourcetitle": null}, {"doi": "10.1179/1743284714Y.0000000714", "title": "Prediction of martensite start temperature", "id": "84941000049", "sourcetitle": "Materials Science and Technology (United Kingdom)"}, {"doi": null, "title": "The effects of alloying elements on the heat treatment of steel", "id": "0003966940", "sourcetitle": "Steel Heat Treat Handb"}, {"doi": "10.1179/1743284711Y.0000000097", "title": "Bainite and martensite start temperature calculated with exponential carbon dependence", "id": "84860427962", "sourcetitle": "Materials Science and Technology"}, {"doi": "10.1002/adem.201300116", "title": "Extension of the martensite transformation temperature relation to larger alloying elements and contents", "id": "84892371585", "sourcetitle": "Advanced Engineering Materials"}, {"doi": "10.2320/matertrans1989.41.761", "title": "Determination of martensite start temperature in engineering steels. Part I. Empirical relations describing the effect of steel chemistry", "id": "0034215901", "sourcetitle": "Materials Transactions, JIM"}, {"doi": null, "title": "The temperature of formation of martensite and bainite in low-alloy steels", "id": "0000441839", "sourcetitle": "J Iron Steel Inst"}, {"doi": null, "title": "Computing A\u201d or ms (transformation temperature on quenching) from analysis", "id": "0001604273", "sourcetitle": "Met Prog"}, {"doi": null, "title": "The temperature range of martensite formation", "id": "0000121783", "sourcetitle": "Trans ASM AIME"}, {"doi": null, "title": "The temperature range of martensite formation", "id": "0000867480", "sourcetitle": "Trans AIME"}, {"doi": null, "title": "The application of the Ms points to case depth measurements", "id": "0002335444", "sourcetitle": "Trans Of the ASM"}, {"doi": null, "title": "EFFECTS OF MICROALLOYING ON THE HARDENABILITY OF STEEL.", "id": "0017920022", "sourcetitle": null}, {"doi": "10.1007/BF02643327", "title": "An examination of the validity of existing empirical formulae for the calculation of ms temperature", "id": "0020091038", "sourcetitle": "Metallurgical Transactions A"}, {"doi": null, "title": "Prediction of Ac1, Ac3 and Ms temperature of steels by empirical formulas", "id": "10444244856", "sourcetitle": "J Japan Soc Heat Treat"}, {"doi": null, "title": "CALCULATING THE CONTINUOUS COOLING TRANSFORMATION CHARACTERISTICS OF STEEL FROM ITS CHEMICAL COMPOSTION", "id": "0014609490", "sourcetitle": "Sumitomo Search"}, {"doi": "10.1016/j.actamat.2017.05.014", "title": "Exploring the microstructure manifold: Image texture representations applied to ultrahigh carbon steel microstructures", "id": "85019539980", "sourcetitle": "Acta Materialia"}, {"doi": "10.1371/journal.pone.0216493", "title": "Large-area, high-resolution characterisation and classification of damage mechanisms in dual-phase steel using deep learning", "id": "85065645106", "sourcetitle": "PLoS ONE"}, {"doi": "10.4028/www.scientific.net/MSF.949.24", "title": "Autonomous interpretation of the microstructure of steels and special alloys", "id": "85071680463", "sourcetitle": "Materials Science Forum"}, {"doi": "10.3390/met9050546", "title": "Texture-based metallurgical phase identification in structural steels: A supervised machine learning approach", "id": "85066764314", "sourcetitle": "Metals"}, {"doi": "10.1080/14686996.2019.1610668", "title": "Automatic steel labeling on certain microstructural constituents with image processing and machine learning tools", "id": "85075937968", "sourcetitle": "Science and Technology of Advanced Materials"}, {"doi": "10.1038/s41598-018-20438-6", "title": "Pattern recognition with machine learning on optical microscopy images of typical metallurgical microstructures", "id": "85041625073", "sourcetitle": "Scientific Reports"}, {"doi": "10.1038/s41598-018-20037-5", "title": "Advanced steel microstructural classification by deep learning methods", "id": "85041616604", "sourcetitle": "Scientific Reports"}, {"doi": "10.1002/adts.201900227", "title": "Property Predictions for Dual-Phase Steels Using Persistent Homology and Machine Learning", "id": "85081009745", "sourcetitle": "Advanced Theory and Simulations"}, {"doi": "10.2355/isijinternational.ISIJINT-2019-089", "title": "Properties-to-microstructure-to-processing inverse analysis for steels via machine learning", "id": "85072271064", "sourcetitle": "ISIJ International"}, {"doi": "10.1016/j.msea.2018.12.049", "title": "Property prediction and properties-to-microstructure inverse analysis of steels by a machine-learning approach", "id": "85058953146", "sourcetitle": "Materials Science and Engineering: A"}, {"doi": "10.1007/s11661-019-05170-8", "title": "Machine Learning to Predict the Martensite Start Temperature in Steels", "id": "85063028004", "sourcetitle": "Metallurgical and Materials Transactions A: Physical Metallurgy and Materials Science"}, {"doi": "10.1007/s10853-006-0881-2", "title": "Artificial neural network modeling for the prediction of critical transformation temperatures in steels", "id": "34547266541", "sourcetitle": "Journal of Materials Science"}, {"doi": "10.2355/isijinternational.42.894", "title": "Determination of Ms temperature in steels: A Bayesian neural network model", "id": "0036392448", "sourcetitle": "ISIJ International"}, {"doi": "10.1179/026708303225001902", "title": "Analysis of effect of alloying elements on martensite start temperature of steels", "id": "0038412806", "sourcetitle": "Materials Science and Technology"}, {"doi": "10.1016/j.commatsci.2005.01.001", "title": "A model for predicting the Ms temperatures of steels", "id": "19944383829", "sourcetitle": "Computational Materials Science"}, {"doi": "10.1016/j.commatsci.2005.01.002", "title": "Critical assessment of models for predicting the Ms temperature of steels", "id": "24044522880", "sourcetitle": "Computational Materials Science"}, {"doi": null, "title": "Prediction of martensite start temperature using artificial neural networks", "id": "0030349735", "sourcetitle": "Ironmaking and Steelmaking"}, {"doi": "10.1016/0956-7151(94)90468-5", "title": "Kinetics of F.C.C. \u2192 B.C.C. heterogeneous martensitic nucleation-I. The critical driving force for athermal nucleation", "id": "0028516163", "sourcetitle": "Acta Metallurgica Et Materialia"}, {"doi": "10.1016/0956-7151(94)90469-3", "title": "Kinetics of F.c.c. \u2192 b.c.c. heterogeneous martensitic nucleation-II. Thermal activation", "id": "0028516164", "sourcetitle": "Acta Metallurgica Et Materialia"}, {"doi": "10.1007/s11661-012-1171-z", "title": "Thermodynamically based prediction of the martensite start temperature for commercial steels", "id": "84867234353", "sourcetitle": "Metallurgical and Materials Transactions A: Physical Metallurgy and Materials Science"}, {"doi": null, "title": "Scikit-learn: Machine learning in Python", "id": "80555140075", "sourcetitle": "Journal of Machine Learning Research"}, {"doi": null, "title": "API design for machine learning software: experiences from the scikit-learn project", "id": "85048193891", "sourcetitle": "arXiv Prepr arXiv13090238"}, {"doi": null, "title": null, "id": "85119447958", "sourcetitle": null}, {"doi": null, "title": null, "id": "85119441272", "sourcetitle": null}, {"doi": "10.1038/323533a0", "title": "Learning representations by back-propagating errors", "id": "0022471098", "sourcetitle": "Nature"}, {"doi": "10.1007/978-3-642-35289-8_3", "title": "Efficient backprop", "id": "84872543023", "sourcetitle": "Lecture Notes in Computer Science (including subseries Lecture Notes in Artificial Intelligence and Lecture Notes in Bioinformatics)"}, {"doi": "10.1023/A:1010933404324", "title": "Random forests", "id": "0035478854", "sourcetitle": "Machine Learning"}, {"doi": "10.1142/9097", "title": "Data Mining with Decision Trees: Theory and Applications, 2nd Edition", "id": "85122017792", "sourcetitle": "Data Mining with Decision Trees: Theory and Applications, 2nd Edition"}, {"doi": "10.1201/9781315139470", "title": "Classification and regression trees", "id": "85052770793", "sourcetitle": "Classification and Regression Trees"}, {"doi": "10.1006/jcss.1997.1504", "title": "A Decision-Theoretic Generalization of On-Line Learning and an Application to Boosting", "id": "0031211090", "sourcetitle": "Journal of Computer and System Sciences"}, {"doi": null, "title": "Improving regressors using boosting techniques", "id": "0000201141", "sourcetitle": "ICML. Citeseer"}, {"doi": "10.1017/CBO9780511812651", "title": "Pattern recognition and neural networks", "id": "84953405534", "sourcetitle": "Pattern Recognition and Neural Networks"}, {"doi": null, "title": null, "id": "0003487601", "sourcetitle": "Neural networks for pattern recognition"}, {"doi": "10.1002/sam.10018", "title": "Neural networks and information in materials science", "id": "70349789252", "sourcetitle": "Statistical Analysis and Data Mining"}]}