{"eid": "2-s2.0-85096950792", "doi": "10.18494/SAM.2020.2774", "pii": null, "pubmed_id": null, "title": "Using machine learning to estimate difficulty levels of problems", "subtype": "ar", "subtypeDescription": "Article", "creator": "Koshino M.", "afid": null, "affilname": "National Institute of Technology, Ishikawa College", "affiliation_city": "Tsubata", "affiliation_country": "Japan", "author_count": null, "author_names": null, "author_ids": null, "author_afids": null, "coverDate": "2020-11-10", "coverDisplayDate": "10 November 2020", "publicationName": "Sensors and Materials", "issn": "09144935", "source_id": "29837", "eIssn": null, "aggregationType": "Journal", "volume": "32", "issueIdentifier": "11", "article_number": null, "pageRange": "3559-3566", "description": null, "authkeywords": null, "citedby_count": 0, "openaccess": 1, "freetoread": "publisherfullgold", "freetoreadLabel": "Gold", "fund_acr": null, "fund_no": null, "fund_sponsor": null, "ref_docs": [{"doi": null, "title": null, "id": "85097000461", "sourcetitle": "Jpn. Soc. Edu. Technol"}, {"doi": null, "title": null, "id": "80052325751", "sourcetitle": "IEICE Trans. Inf. Syst. (Japanese edition)"}, {"doi": "10.1541/ieejeiss.131.800", "title": "Estimation of users' subjective difficulty of WEB based English listening tests", "id": "80052322620", "sourcetitle": "IEEJ Transactions on Electronics, Information and Systems"}, {"doi": null, "title": null, "id": "85096986718", "sourcetitle": "Tech. Rep. IEICE"}, {"doi": "10.1109/BSN.2017.7935996", "title": "Modeling and detecting student attention and interest level using wearable computers", "id": "85025445328", "sourcetitle": "2017 IEEE 14th International Conference on Wearable and Implantable Body Sensor Networks, BSN 2017"}, {"doi": null, "title": null, "id": "85096976930", "sourcetitle": "SIG Adv. Learning Sci. Technol"}, {"doi": null, "title": null, "id": "85096965108", "sourcetitle": "Jpn. Soc. Inf. Syst. Edu"}, {"doi": null, "title": null, "id": "85096970604", "sourcetitle": "Jpn. Soc. Fuzzy Theory Intell. Inf"}, {"doi": null, "title": null, "id": "85096990747", "sourcetitle": "IPSJ SIG Tech. Rep. CVIM 2017-CVIM-209"}, {"doi": null, "title": null, "id": "85096998515", "sourcetitle": "Proc. Annu. Conf. Japanese Society for Information and Systems in Education"}, {"doi": null, "title": null, "id": "85096997227", "sourcetitle": "Proc. IEEE 18th Int. Symp. A World of Wireless, Mobile and Multimedia Networks (WoWMoM)"}, {"doi": null, "title": null, "id": "85050017882", "sourcetitle": "Jpn. Soc. Fuzzy Theory Intell. Inf"}, {"doi": null, "title": null, "id": "85096959276", "sourcetitle": "IEEJ Trans. Electron. Inf. Syst"}, {"doi": null, "title": null, "id": "85096965508", "sourcetitle": "Jpn. Soc. Inf. Syst. Edu"}, {"doi": null, "title": null, "id": "85096964499", "sourcetitle": "IPSJ Interaction"}, {"doi": "10.1016/j.ifacol.2016.10.571", "title": "Human Cognitive Control Mode Estimation Using JINS MEME", "id": "84994894133", "sourcetitle": "IFAC-PapersOnLine"}, {"doi": null, "title": null, "id": "85096949964", "sourcetitle": "Memoirs of Hokkaido Information University"}, {"doi": "10.1109/TENCON.2018.8650315", "title": "Estimation of degree of retention and subjective difficulty of four-choice English vocabulary questions using a wearable device", "id": "85063230153", "sourcetitle": "IEEE Region 10 Annual International Conference, Proceedings/TENCON"}]}