{"eid": "2-s2.0-85089190483", "doi": "10.1021/acs.jpclett.0c01846", "pii": null, "pubmed_id": "32698581", "title": "Machine-Intelligence-Driven High-Throughput Prediction of 2D Charge Density Wave Phases", "subtype": "ar", "subtypeDescription": "Article", "creator": "Kabiraj A.", "afid": null, "affilname": "Indian Institute of Science", "affiliation_city": "Bengaluru", "affiliation_country": "India", "author_count": null, "author_names": null, "author_ids": null, "author_afids": null, "coverDate": "2020-08-06", "coverDisplayDate": "6 August 2020", "publicationName": "Journal of Physical Chemistry Letters", "issn": null, "source_id": "19600166212", "eIssn": "19487185", "aggregationType": "Journal", "volume": "11", "issueIdentifier": "15", "article_number": null, "pageRange": "6291-6298", "description": null, "authkeywords": null, "citedby_count": 6, "openaccess": 0, "freetoread": "repositoryam", "freetoreadLabel": "Green", "fund_acr": null, "fund_no": null, "fund_sponsor": null, "ref_docs": [{"doi": "10.1063/1.881498", "title": "Charge-density-wave conductors", "id": "0030151483", "sourcetitle": "Physics Today"}, {"doi": null, "title": null, "id": "0003884610", "sourcetitle": "Quantum Theory of Solids"}, {"doi": "10.1103/PhysRevLett.2.393", "title": "Image of the fermi surface in the vibration spectrum of a metal", "id": "0000701138", "sourcetitle": "Physical Review Letters"}, {"doi": "10.1073/pnas.1424791112", "title": "Classification of charge density waves based on their nature", "id": "84923666756", "sourcetitle": "Proceedings of the National Academy of Sciences of the United States of America"}, {"doi": "10.1088/0034-4885/79/8/084505", "title": "Charge density waves in strongly correlated electron systems", "id": "84980050692", "sourcetitle": "Reports on Progress in Physics"}, {"doi": "10.1103/PhysRevB.73.205102", "title": "Fermi-surface nesting and the origin of the charge-density wave in Nb Se2", "id": "34547824430", "sourcetitle": "Physical Review B - Condensed Matter and Materials Physics"}, {"doi": "10.1103/PhysRevB.77.165135", "title": "Fermi surface nesting and the origin of charge density waves in metals", "id": "43049105742", "sourcetitle": "Physical Review B - Condensed Matter and Materials Physics"}, {"doi": "10.1073/pnas.1512092112", "title": "Structure and control of charge density waves in two-dimensional 1T-TaS2", "id": "84949309765", "sourcetitle": "Proceedings of the National Academy of Sciences of the United States of America"}, {"doi": "10.1126/sciadv.1500606", "title": "Memristive phase switching in two-dimensional 1T-TaS2 crystals", "id": "85022149449", "sourcetitle": "Science Advances"}, {"doi": "10.1126/science.1241591", "title": "Ultrafast switching to a stable hidden quantum state in an electronic crystal", "id": "84897971491", "sourcetitle": "Science"}, {"doi": "10.1038/nnano.2016.108", "title": "A charge-density-wave oscillator based on an integrated tantalum disulfide-boron nitride-graphene device operating at room temperature", "id": "84976870589", "sourcetitle": "Nature Nanotechnology"}, {"doi": "10.1063/1.5138964", "title": "Memristive phase switching in two-dimensional 1T\u2032-VSe2 crystals", "id": "85078424906", "sourcetitle": "Applied Physics Letters"}, {"doi": "10.1109/LED.2018.2858244", "title": "Transistor-Less Logic Circuits Implemented with 2-D Charge Density Wave Devices", "id": "85050408541", "sourcetitle": "IEEE Electron Device Letters"}, {"doi": "10.1109/TNANO.2017.2716845", "title": "Two-dimensional oscillatory neural network based on room-temperature charge-density-wave devices", "id": "85021824378", "sourcetitle": "IEEE Transactions on Nanotechnology"}, {"doi": "10.1126/science.1102896", "title": "Electric field in atomically thin carbon films", "id": "7444220645", "sourcetitle": "Science"}, {"doi": "10.1080/10408436.2013.836075", "title": "Synthesis, properties, and applications of 2-D materials: A comprehensive review", "id": "84899054976", "sourcetitle": "Critical Reviews in Solid State and Materials Sciences"}, {"doi": "10.1038/nnano.2015.143", "title": "Strongly enhanced charge-density-wave order in monolayer NbSe 2", "id": "84941191472", "sourcetitle": "Nature Nanotechnology"}, {"doi": "10.1021/acs.nanolett.7b03264", "title": "Persistent Charge-Density-Wave Order in Single-Layer TaSe2", "id": "85042065730", "sourcetitle": "Nano Letters"}, {"doi": "10.1038/ncomms9943", "title": "Charge density wave transition in single-layer titanium diselenide", "id": "84947713415", "sourcetitle": "Nature Communications"}, {"doi": "10.1021/acs.nanolett.8b00729", "title": "Low-Frequency Current Fluctuations and Sliding of the Charge Density Waves in Two-Dimensional Materials", "id": "85047385377", "sourcetitle": "Nano Letters"}, {"doi": "10.1021/acsnano.9b02870", "title": "Bias-Voltage Driven Switching of the Charge-Density-Wave and Normal Metallic Phases in 1T-TaS2 Thin-Film Devices", "id": "85068515831", "sourcetitle": "ACS Nano"}, {"doi": "10.1039/c9nr01614g", "title": "Proton-irradiation-immune electronics implemented with two-dimensional charge-density-wave devices", "id": "85064896129", "sourcetitle": "Nanoscale"}, {"doi": "10.1063/5.0007043", "title": "High-frequency current oscillations in charge-density-wave 1T-TaS2 devices: Revisiting the \"narrow band noise\" concept", "id": "85083959089", "sourcetitle": "Applied Physics Letters"}, {"doi": "10.1021/acs.nanolett.8b00237", "title": "Unveiling Charge-Density Wave, Superconductivity, and Their Competitive Nature in Two-Dimensional NbSe2", "id": "85046114802", "sourcetitle": "Nano Letters"}, {"doi": "10.1103/PhysRevLett.122.016403", "title": "Topological Landscape of Competing Charge Density Waves in 2H-NbSe2", "id": "85059870790", "sourcetitle": "Physical Review Letters"}, {"doi": "10.1038/nphys3527", "title": "Characterization of collective ground states in single-layer NbSe 2", "id": "84954076212", "sourcetitle": "Nature Physics"}, {"doi": "10.1103/PhysRevB.98.195419", "title": "Unveiling hidden charge density waves in single-layer NbSe2 by impurities", "id": "85056632145", "sourcetitle": "Physical Review B"}, {"doi": "10.1103/PhysRevB.97.045133", "title": "Charge density wave states in tantalum dichalcogenides", "id": "85040953810", "sourcetitle": "Physical Review B"}, {"doi": "10.1103/PhysRevB.97.041413", "title": "Coupling of charge, lattice, orbital, and spin degrees of freedom in charge density waves in 1 T- TaS 2", "id": "85041112663", "sourcetitle": "Physical Review B"}, {"doi": "10.1021/acs.nanolett.9b02689", "title": "Relative Abundance of Z 2 Topological Order in Exfoliable Two-Dimensional Insulators", "id": "85076450404", "sourcetitle": "Nano Letters"}, {"doi": "10.1038/s41524-020-0300-2", "title": "High-throughput discovery of high Curie point two-dimensional ferromagnetic materials", "id": "85083155049", "sourcetitle": "npj Computational Materials"}, {"doi": "10.1021/acsenergylett.9b02689", "title": "Catalytic Activity and Stability of Two-Dimensional Materials for the Hydrogen Evolution Reaction", "id": "85080061492", "sourcetitle": "ACS Energy Letters"}, {"doi": "10.1038/s41565-017-0035-5", "title": "Two-dimensional materials from high-throughput computational exfoliation of experimentally known compounds", "id": "85041631624", "sourcetitle": "Nature Nanotechnology"}, {"doi": "10.1103/PhysRevB.96.165305", "title": "Doping-controlled phase transitions in single-layer MoS2", "id": "85038107621", "sourcetitle": "Physical Review B"}, {"doi": "10.1088/1361-648X/aaac95", "title": "Origin of distorted 1T-phase ReS2: First-principles study", "id": "85042288828", "sourcetitle": "Journal of Physics Condensed Matter"}, {"doi": "10.1088/0953-8984/23/5/053201", "title": "Ab initio random structure searching", "id": "79551662789", "sourcetitle": "Journal of Physics Condensed Matter"}, {"doi": "10.1021/acs.jpcc.9b09477", "title": "Intercalation-Driven Reversible Switching of 2D Magnetism", "id": "85089199984", "sourcetitle": "Journal of Physical Chemistry C"}, {"doi": "10.1109/34.1000236", "title": "Mean shift: A robust approach toward feature space analysis", "id": "0036565814", "sourcetitle": "IEEE Transactions on Pattern Analysis and Machine Intelligence"}, {"doi": null, "title": "Review of Mean Shift Algorithm and Its Improvements", "id": "85090379305", "sourcetitle": "Ijca Proc. Int. Conf. Comput. Technol."}, {"doi": "10.1209/0295-5075/115/47001", "title": "Dimensionality-driven phonon softening and incipient charge density wave instability in TiS2", "id": "84991670431", "sourcetitle": "EPL"}]}