{"eid": "2-s2.0-85032332635", "doi": "10.1080/14686996.2017.1371559", "pii": null, "pubmed_id": null, "title": "Petascale supercomputing to accelerate the design of high-temperature alloys", "subtype": "ar", "subtypeDescription": "Article", "creator": "Shin D.", "afid": null, "affilname": "Oak Ridge National Laboratory", "affiliation_city": "Oak Ridge", "affiliation_country": "United States", "author_count": null, "author_names": null, "author_ids": null, "author_afids": null, "coverDate": "2017-12-31", "coverDisplayDate": "31 December 2017", "publicationName": "Science and Technology of Advanced Materials", "issn": "14686996", "source_id": "17918", "eIssn": "18785514", "aggregationType": "Journal", "volume": "18", "issueIdentifier": "1", "article_number": null, "pageRange": "828-838", "description": null, "authkeywords": null, "citedby_count": 14, "openaccess": 1, "freetoread": "repositoryam", "freetoreadLabel": "Green", "fund_acr": null, "fund_no": null, "fund_sponsor": null, "ref_docs": [{"doi": null, "title": null, "id": "85032385560", "sourcetitle": "Cast aluminum alloys with extreme microstructural stability at elevated temperature"}, {"doi": "10.1103/PhysRev.140.A1133", "title": "Self-consistent equations including exchange and correlation effects", "id": "0042113153", "sourcetitle": "Physical Review"}, {"doi": "10.1016/j.actamat.2011.06.036", "title": "Precipitates in Al-Cu alloys revisited: Atom-probe tomographic experiments and first-principles calculations of compositional evolution and interfacial segregation", "id": "79961011893", "sourcetitle": "Acta Materialia"}, {"doi": "10.1016/j.actamat.2017.09.020", "title": "Solute segregation at the Al/\u03b8\u2032-Al2Cu interface in Al-Cu alloys", "id": "85029798414", "sourcetitle": "Acta Materialia"}, {"doi": "10.1016/0927-0256(96)00008-0", "title": "Efficiency of ab-initio total energy calculations for metals and semiconductors using a plane-wave basis set", "id": "0030190741", "sourcetitle": "Computational Materials Science"}, {"doi": "10.1103/PhysRevB.54.11169", "title": "Efficient iterative schemes for ab initio total-energy calculations using a plane-wave basis set", "id": "2442537377", "sourcetitle": "Physical Review B - Condensed Matter and Materials Physics"}, {"doi": "10.1103/PhysRevB.59.1758", "title": "From ultrasoft pseudopotentials to the projector augmented-wave method", "id": "0011236321", "sourcetitle": "Physical Review B - Condensed Matter and Materials Physics"}, {"doi": "10.1103/PhysRevB.45.13244", "title": "Accurate and simple analytic representation of the electron-gas correlation energy", "id": "33645898818", "sourcetitle": "Physical Review B"}, {"doi": "10.1103/PhysRevLett.77.3865", "title": "Generalized gradient approximation made simple", "id": "4243943295", "sourcetitle": "Physical Review Letters"}, {"doi": "10.1103/PhysRevLett.65.353", "title": "Special quasirandom structures", "id": "0000214080", "sourcetitle": "Physical Review Letters"}, {"doi": "10.1016/j.actamat.2007.06.039", "title": "Solute-vacancy binding in aluminum", "id": "34548692056", "sourcetitle": "Acta Materialia"}, {"doi": "10.1016/j.actamat.2009.09.031", "title": "First-principles study of solute-vacancy binding in magnesium", "id": "70449476990", "sourcetitle": "Acta Materialia"}, {"doi": "10.1126/science.1205438", "title": "Detecting novel associations in large data sets", "id": "83755163018", "sourcetitle": "Science"}, {"doi": null, "title": "Scikit-learn: Machine learning in Python", "id": "80555140075", "sourcetitle": "Journal of Machine Learning Research"}, {"doi": null, "title": null, "id": "0003973174", "sourcetitle": "Applied linear statistical models"}, {"doi": null, "title": "Learning Gaussian processes from multiple tasks", "id": "31844442664", "sourcetitle": "ICML 2005 - Proceedings of the 22nd International Conference on Machine Learning"}, {"doi": null, "title": "Divide and conquer kernel ridge regression", "id": "84940542624", "sourcetitle": "Conf Learn Theory"}, {"doi": "10.1162/089976603321891864", "title": "Comparison of model selection for regression", "id": "0037484691", "sourcetitle": "Neural Computation"}, {"doi": null, "title": "Machine learning benchmarks and random forest regression", "id": "82955250352", "sourcetitle": "Biostatistics"}, {"doi": "10.1016/j.actamat.2016.08.013", "title": "The influence of Sc solute partitioning on the microalloying effect and mechanical properties of Al-Cu alloys with minor Sc addition", "id": "84981313827", "sourcetitle": "Acta Materialia"}, {"doi": "10.1016/j.actamat.2012.11.043", "title": "Effect of interfacial solute segregation on ductile fracture of Al-Cu-Sc alloys", "id": "84873733650", "sourcetitle": "Acta Materialia"}]}